Metadata-Version: 2.1
Name: umidcalculator
Version: 0.0.1
Summary: Basic calculator
Home-page: 
Author: Umidyor
Author-email: actualnew001@gmail.com
License: MIT
Keywords: calculator
Classifier: Development Status :: 5 - Production/Stable
Classifier: Intended Audience :: Education
Classifier: Operating System :: Microsoft :: Windows :: Windows 10
Classifier: License :: OSI Approved :: MIT License
Classifier: Programming Language :: Python :: 3
License-File: LICENCE.txt
